aiotapioca_yandex_metrika/__init__.py
aiotapioca_yandex_metrika/__version__.py
aiotapioca_yandex_metrika/aiotapioca_yandex_metrika.py
aiotapioca_yandex_metrika/exceptions.py
aiotapioca_yandex_metrika/parsers.py
aiotapioca_yandex_metrika/py.typed
aiotapioca_yandex_metrika/resource_mapping.py
aiotapioca_yandex_metrika-2022.11.7.dist-info/WHEEL
aiotapioca_yandex_metrika-2022.11.7.dist-info/METADATA
aiotapioca_yandex_metrika-2022.11.7.dist-info/licenses/LICENSE
aiotapioca_yandex_metrika-2022.11.7.dist-info/RECORD
