Metadata-Version: 2.1
Name: aiotapioca-yandex-metrika
Version: 2022.11.7
Summary: Python asynchronous I/O client for API Yandex Metrika
License: MIT
Keywords: async,asyncio,aiotapioca,tapioca,wrapper,api,yandex,metrika
Author-email: Pavel Maksimov <vur21@ya.ru>,Andrey Ilin <andreyilin@fastmail.com>
Requires-Python: >=3.7
Classifier: Development Status :: 5 - Production/Stable
Classifier: Intended Audience :: Developers
Classifier: License :: OSI Approved :: MIT License
Classifier: Programming Language :: Python
Classifier: Programming Language :: Python :: 3
Classifier: Programming Language :: Python :: 3.10
Classifier: Programming Language :: Python :: 3.11
Classifier: Programming Language :: Python :: 3.12
Classifier: Programming Language :: Python :: 3.7
Classifier: Programming Language :: Python :: 3.8
Classifier: Programming Language :: Python :: 3.9
Classifier: Programming Language :: Python :: Implementation :: CPython
Classifier: Topic :: Internet :: WWW/HTTP
Classifier: Topic :: Software Development :: Libraries :: Python Modules
Requires-Dist: aiotapioca-wrapper>=4.0.1
